LICENSE
MANIFEST.in
README.md
setup.py
mkzbomb/mkzbomb.py
mkzbomb/progress.py
mkzbomb.egg-info/PKG-INFO
mkzbomb.egg-info/SOURCES.txt
mkzbomb.egg-info/dependency_links.txt
mkzbomb.egg-info/entry_points.txt
mkzbomb.egg-info/top_level.txt