Metadata-Version: 1.1
Name: mkzbomb
Version: 1.0.2
Summary: ZipBomb builder
Home-page: https://github.com/jacopodl/mkzbomb
Author: Jacopo De Luca
Author-email: jacopo.delu@gmail.com
License: GNU General Public License v3
Keywords: zbomb zipbomb zip bomb hacking-tool
Platform: UNKNOWN
Classifier: Development Status :: 5 - Production/Stable
Classifier: Intended Audience :: Developers
Classifier: License :: OSI Approved :: GNU General Public License v3 or later (GPLv3+)
Classifier: Programming Language :: Python :: 3
